cz_conventional_jira.py
commitizen_conventional_jira-1.0.0.dist-info/METADATA
commitizen_conventional_jira-1.0.0.dist-info/WHEEL
commitizen_conventional_jira-1.0.0.dist-info/top_level.txt
commitizen_conventional_jira-1.0.0.dist-info/RECORD
