Metadata-Version: 2.1
Name: commitizen-conventional-jira
Version: 1.0.0
Summary: An extension of the conventional commits to include JIRA issues.
Home-page: https://gitlab.com/kentharold/commitizen-conventional-jira
Author: Kent Harold Mbatchakwe
Author-email: mbatchakwe.kentharold@gmail.com
License: MIT
Platform: UNKNOWN
Requires-Dist: commitizen
